{
    "circuit837.qasm": {
        "outcome_sum": 5,
        "n_failed_trap_rounds": 0,
        "outcome": "Ambig.",
        "failure_rate": 0.0
    },
    "circuit790.qasm": {
        "outcome_sum": 5,
        "n_failed_trap_rounds": 2,
        "outcome": "Ambig.",
        "failure_rate": 0.2
    },
    "circuit234.qasm": {
        "outcome_sum": 1,
        "n_failed_trap_rounds": 1,
        "outcome": 0,
        "failure_rate": 0.1
    },
    "circuit928.qasm": {
        "outcome_sum": 2,
        "n_failed_trap_rounds": 2,
        "outcome": 0,
        "failure_rate": 0.2
    },
    "circuit723.qasm": {
        "outcome_sum": 0,
        "n_failed_trap_rounds": 1,
        "outcome": 0,
        "failure_rate": 0.1
    },
    "circuit685.qasm": {
        "outcome_sum": 2,
        "n_failed_trap_rounds": 3,
        "outcome": 0,
        "failure_rate": 0.3
    },
    "circuit978.qasm": {
        "outcome_sum": 3,
        "n_failed_trap_rounds": 1,
        "outcome": 0,
        "failure_rate": 0.1
    },
    "circuit748.qasm": {
        "outcome_sum": 0,
        "n_failed_trap_rounds": 0,
        "outcome": 0,
        "failure_rate": 0.0
    },
    "circuit588.qasm": {
        "outcome_sum": 2,
        "n_failed_trap_rounds": 0,
        "outcome": 0,
        "failure_rate": 0.0
    },
    "circuit796.qasm": {
        "outcome_sum": 0,
        "n_failed_trap_rounds": 2,
        "outcome": 0,
        "failure_rate": 0.2
    }
}