{
    "circuit951.qasm": {
        "outcome_sum": 0,
        "n_failed_trap_rounds": 0,
        "outcome": 0,
        "failure_rate": 0.0
    },
    "circuit483.qasm": {
        "outcome_sum": 10,
        "n_failed_trap_rounds": 1,
        "outcome": 1,
        "failure_rate": 0.1
    },
    "circuit439.qasm": {
        "outcome_sum": 4,
        "n_failed_trap_rounds": 1,
        "outcome": 0,
        "failure_rate": 0.1
    },
    "circuit674.qasm": {
        "outcome_sum": 1,
        "n_failed_trap_rounds": 1,
        "outcome": 0,
        "failure_rate": 0.1
    },
    "circuit444.qasm": {
        "outcome_sum": 6,
        "n_failed_trap_rounds": 2,
        "outcome": 1,
        "failure_rate": 0.2
    },
    "circuit633.qasm": {
        "outcome_sum": 8,
        "n_failed_trap_rounds": 0,
        "outcome": 1,
        "failure_rate": 0.0
    },
    "circuit039.qasm": {
        "outcome_sum": 5,
        "n_failed_trap_rounds": 1,
        "outcome": "Ambig.",
        "failure_rate": 0.1
    },
    "circuit440.qasm": {
        "outcome_sum": 0,
        "n_failed_trap_rounds": 2,
        "outcome": 0,
        "failure_rate": 0.2
    },
    "circuit878.qasm": {
        "outcome_sum": 7,
        "n_failed_trap_rounds": 1,
        "outcome": 1,
        "failure_rate": 0.1
    },
    "circuit443.qasm": {
        "outcome_sum": 5,
        "n_failed_trap_rounds": 2,
        "outcome": "Ambig.",
        "failure_rate": 0.2
    },
    "circuit591.qasm": {
        "outcome_sum": 2,
        "n_failed_trap_rounds": 2,
        "outcome": 0,
        "failure_rate": 0.2
    },
    "circuit686.qasm": {
        "outcome_sum": 1,
        "n_failed_trap_rounds": 0,
        "outcome": 0,
        "failure_rate": 0.0
    },
    "circuit740.qasm": {
        "outcome_sum": 4,
        "n_failed_trap_rounds": 0,
        "outcome": 0,
        "failure_rate": 0.0
    },
    "circuit767.qasm": {
        "outcome_sum": 6,
        "n_failed_trap_rounds": 2,
        "outcome": 1,
        "failure_rate": 0.2
    },
    "circuit257.qasm": {
        "outcome_sum": 7,
        "n_failed_trap_rounds": 0,
        "outcome": 1,
        "failure_rate": 0.0
    },
    "circuit836.qasm": {
        "outcome_sum": 4,
        "n_failed_trap_rounds": 0,
        "outcome": 0,
        "failure_rate": 0.0
    },
    "circuit578.qasm": {
        "outcome_sum": 2,
        "n_failed_trap_rounds": 3,
        "outcome": 0,
        "failure_rate": 0.3
    },
    "circuit397.qasm": {
        "outcome_sum": 0,
        "n_failed_trap_rounds": 1,
        "outcome": 0,
        "failure_rate": 0.1
    },
    "circuit545.qasm": {
        "outcome_sum": 5,
        "n_failed_trap_rounds": 3,
        "outcome": "Ambig.",
        "failure_rate": 0.3
    },
    "circuit925.qasm": {
        "outcome_sum": 8,
        "n_failed_trap_rounds": 1,
        "outcome": 1,
        "failure_rate": 0.1
    },
    "circuit186.qasm": {
        "outcome_sum": 10,
        "n_failed_trap_rounds": 1,
        "outcome": 1,
        "failure_rate": 0.1
    },
    "circuit718.qasm": {
        "outcome_sum": 5,
        "n_failed_trap_rounds": 0,
        "outcome": "Ambig.",
        "failure_rate": 0.0
    },
    "circuit490.qasm": {
        "outcome_sum": 2,
        "n_failed_trap_rounds": 0,
        "outcome": 0,
        "failure_rate": 0.0
    },
    "circuit905.qasm": {
        "outcome_sum": 5,
        "n_failed_trap_rounds": 0,
        "outcome": "Ambig.",
        "failure_rate": 0.0
    },
    "circuit743.qasm": {
        "outcome_sum": 10,
        "n_failed_trap_rounds": 0,
        "outcome": 1,
        "failure_rate": 0.0
    },
    "circuit384.qasm": {
        "outcome_sum": 8,
        "n_failed_trap_rounds": 0,
        "outcome": 1,
        "failure_rate": 0.0
    },
    "circuit810.qasm": {
        "outcome_sum": 10,
        "n_failed_trap_rounds": 0,
        "outcome": 1,
        "failure_rate": 0.0
    },
    "circuit682.qasm": {
        "outcome_sum": 9,
        "n_failed_trap_rounds": 2,
        "outcome": 1,
        "failure_rate": 0.2
    },
    "circuit243.qasm": {
        "outcome_sum": 0,
        "n_failed_trap_rounds": 1,
        "outcome": 0,
        "failure_rate": 0.1
    },
    "circuit966.qasm": {
        "outcome_sum": 4,
        "n_failed_trap_rounds": 0,
        "outcome": 0,
        "failure_rate": 0.0
    },
    "circuit170.qasm": {
        "outcome_sum": 4,
        "n_failed_trap_rounds": 0,
        "outcome": 0,
        "failure_rate": 0.0
    },
    "circuit957.qasm": {
        "outcome_sum": 6,
        "n_failed_trap_rounds": 1,
        "outcome": 1,
        "failure_rate": 0.1
    },
    "circuit529.qasm": {
        "outcome_sum": 7,
        "n_failed_trap_rounds": 0,
        "outcome": 1,
        "failure_rate": 0.0
    },
    "circuit654.qasm": {
        "outcome_sum": 2,
        "n_failed_trap_rounds": 1,
        "outcome": 0,
        "failure_rate": 0.1
    },
    "circuit927.qasm": {
        "outcome_sum": 5,
        "n_failed_trap_rounds": 0,
        "outcome": "Ambig.",
        "failure_rate": 0.0
    },
    "circuit109.qasm": {
        "outcome_sum": 9,
        "n_failed_trap_rounds": 0,
        "outcome": 1,
        "failure_rate": 0.0
    },
    "circuit305.qasm": {
        "outcome_sum": 5,
        "n_failed_trap_rounds": 1,
        "outcome": "Ambig.",
        "failure_rate": 0.1
    },
    "circuit881.qasm": {
        "outcome_sum": 1,
        "n_failed_trap_rounds": 2,
        "outcome": 0,
        "failure_rate": 0.2
    },
    "circuit780.qasm": {
        "outcome_sum": 9,
        "n_failed_trap_rounds": 0,
        "outcome": 1,
        "failure_rate": 0.0
    },
    "circuit623.qasm": {
        "outcome_sum": 2,
        "n_failed_trap_rounds": 0,
        "outcome": 0,
        "failure_rate": 0.0
    },
    "circuit978.qasm": {
        "outcome_sum": 8,
        "n_failed_trap_rounds": 1,
        "outcome": 1,
        "failure_rate": 0.1
    },
    "circuit861.qasm": {
        "outcome_sum": 8,
        "n_failed_trap_rounds": 1,
        "outcome": 1,
        "failure_rate": 0.1
    },
    "circuit656.qasm": {
        "outcome_sum": 5,
        "n_failed_trap_rounds": 0,
        "outcome": "Ambig.",
        "failure_rate": 0.0
    },
    "circuit812.qasm": {
        "outcome_sum": 1,
        "n_failed_trap_rounds": 1,
        "outcome": 0,
        "failure_rate": 0.1
    },
    "circuit866.qasm": {
        "outcome_sum": 0,
        "n_failed_trap_rounds": 3,
        "outcome": 0,
        "failure_rate": 0.3
    },
    "circuit804.qasm": {
        "outcome_sum": 4,
        "n_failed_trap_rounds": 0,
        "outcome": 0,
        "failure_rate": 0.0
    },
    "circuit569.qasm": {
        "outcome_sum": 1,
        "n_failed_trap_rounds": 0,
        "outcome": 0,
        "failure_rate": 0.0
    },
    "circuit106.qasm": {
        "outcome_sum": 0,
        "n_failed_trap_rounds": 0,
        "outcome": 0,
        "failure_rate": 0.0
    },
    "circuit560.qasm": {
        "outcome_sum": 1,
        "n_failed_trap_rounds": 0,
        "outcome": 0,
        "failure_rate": 0.0
    },
    "circuit732.qasm": {
        "outcome_sum": 5,
        "n_failed_trap_rounds": 1,
        "outcome": "Ambig.",
        "failure_rate": 0.1
    },
    "circuit993.qasm": {
        "outcome_sum": 0,
        "n_failed_trap_rounds": 0,
        "outcome": 0,
        "failure_rate": 0.0
    },
    "circuit778.qasm": {
        "outcome_sum": 0,
        "n_failed_trap_rounds": 0,
        "outcome": 0,
        "failure_rate": 0.0
    },
    "circuit557.qasm": {
        "outcome_sum": 7,
        "n_failed_trap_rounds": 0,
        "outcome": 1,
        "failure_rate": 0.0
    },
    "circuit076.qasm": {
        "outcome_sum": 10,
        "n_failed_trap_rounds": 1,
        "outcome": 1,
        "failure_rate": 0.1
    },
    "circuit074.qasm": {
        "outcome_sum": 9,
        "n_failed_trap_rounds": 0,
        "outcome": 1,
        "failure_rate": 0.0
    },
    "circuit116.qasm": {
        "outcome_sum": 2,
        "n_failed_trap_rounds": 2,
        "outcome": 0,
        "failure_rate": 0.2
    },
    "circuit491.qasm": {
        "outcome_sum": 3,
        "n_failed_trap_rounds": 0,
        "outcome": 0,
        "failure_rate": 0.0
    },
    "circuit422.qasm": {
        "outcome_sum": 8,
        "n_failed_trap_rounds": 0,
        "outcome": 1,
        "failure_rate": 0.0
    },
    "circuit128.qasm": {
        "outcome_sum": 8,
        "n_failed_trap_rounds": 2,
        "outcome": 1,
        "failure_rate": 0.2
    },
    "circuit640.qasm": {
        "outcome_sum": 1,
        "n_failed_trap_rounds": 1,
        "outcome": 0,
        "failure_rate": 0.1
    },
    "circuit099.qasm": {
        "outcome_sum": 6,
        "n_failed_trap_rounds": 0,
        "outcome": 1,
        "failure_rate": 0.0
    },
    "circuit670.qasm": {
        "outcome_sum": 9,
        "n_failed_trap_rounds": 1,
        "outcome": 1,
        "failure_rate": 0.1
    },
    "circuit863.qasm": {
        "outcome_sum": 0,
        "n_failed_trap_rounds": 2,
        "outcome": 0,
        "failure_rate": 0.2
    },
    "circuit523.qasm": {
        "outcome_sum": 3,
        "n_failed_trap_rounds": 0,
        "outcome": 0,
        "failure_rate": 0.0
    },
    "circuit152.qasm": {
        "outcome_sum": 2,
        "n_failed_trap_rounds": 1,
        "outcome": 0,
        "failure_rate": 0.1
    },
    "circuit835.qasm": {
        "outcome_sum": 4,
        "n_failed_trap_rounds": 0,
        "outcome": 0,
        "failure_rate": 0.0
    },
    "circuit248.qasm": {
        "outcome_sum": 3,
        "n_failed_trap_rounds": 0,
        "outcome": 0,
        "failure_rate": 0.0
    },
    "circuit531.qasm": {
        "outcome_sum": 10,
        "n_failed_trap_rounds": 3,
        "outcome": 1,
        "failure_rate": 0.3
    },
    "circuit955.qasm": {
        "outcome_sum": 5,
        "n_failed_trap_rounds": 2,
        "outcome": "Ambig.",
        "failure_rate": 0.2
    },
    "circuit853.qasm": {
        "outcome_sum": 9,
        "n_failed_trap_rounds": 2,
        "outcome": 1,
        "failure_rate": 0.2
    },
    "circuit110.qasm": {
        "outcome_sum": 7,
        "n_failed_trap_rounds": 2,
        "outcome": 1,
        "failure_rate": 0.2
    },
    "circuit848.qasm": {
        "outcome_sum": 10,
        "n_failed_trap_rounds": 0,
        "outcome": 1,
        "failure_rate": 0.0
    },
    "circuit668.qasm": {
        "outcome_sum": 4,
        "n_failed_trap_rounds": 2,
        "outcome": 0,
        "failure_rate": 0.2
    },
    "circuit513.qasm": {
        "outcome_sum": 1,
        "n_failed_trap_rounds": 0,
        "outcome": 0,
        "failure_rate": 0.0
    },
    "circuit421.qasm": {
        "outcome_sum": 0,
        "n_failed_trap_rounds": 1,
        "outcome": 0,
        "failure_rate": 0.1
    },
    "circuit681.qasm": {
        "outcome_sum": 5,
        "n_failed_trap_rounds": 3,
        "outcome": "Ambig.",
        "failure_rate": 0.3
    },
    "circuit526.qasm": {
        "outcome_sum": 0,
        "n_failed_trap_rounds": 0,
        "outcome": 0,
        "failure_rate": 0.0
    },
    "circuit678.qasm": {
        "outcome_sum": 6,
        "n_failed_trap_rounds": 0,
        "outcome": 1,
        "failure_rate": 0.0
    },
    "circuit117.qasm": {
        "outcome_sum": 3,
        "n_failed_trap_rounds": 0,
        "outcome": 0,
        "failure_rate": 0.0
    },
    "circuit530.qasm": {
        "outcome_sum": 10,
        "n_failed_trap_rounds": 1,
        "outcome": 1,
        "failure_rate": 0.1
    },
    "circuit198.qasm": {
        "outcome_sum": 0,
        "n_failed_trap_rounds": 1,
        "outcome": 0,
        "failure_rate": 0.1
    },
    "circuit414.qasm": {
        "outcome_sum": 10,
        "n_failed_trap_rounds": 1,
        "outcome": 1,
        "failure_rate": 0.1
    },
    "circuit211.qasm": {
        "outcome_sum": 9,
        "n_failed_trap_rounds": 2,
        "outcome": 1,
        "failure_rate": 0.2
    },
    "circuit771.qasm": {
        "outcome_sum": 0,
        "n_failed_trap_rounds": 0,
        "outcome": 0,
        "failure_rate": 0.0
    },
    "circuit895.qasm": {
        "outcome_sum": 6,
        "n_failed_trap_rounds": 1,
        "outcome": 1,
        "failure_rate": 0.1
    },
    "circuit175.qasm": {
        "outcome_sum": 5,
        "n_failed_trap_rounds": 0,
        "outcome": "Ambig.",
        "failure_rate": 0.0
    },
    "circuit690.qasm": {
        "outcome_sum": 8,
        "n_failed_trap_rounds": 0,
        "outcome": 1,
        "failure_rate": 0.0
    },
    "circuit693.qasm": {
        "outcome_sum": 6,
        "n_failed_trap_rounds": 0,
        "outcome": 1,
        "failure_rate": 0.0
    },
    "circuit542.qasm": {
        "outcome_sum": 2,
        "n_failed_trap_rounds": 0,
        "outcome": 0,
        "failure_rate": 0.0
    },
    "circuit326.qasm": {
        "outcome_sum": 8,
        "n_failed_trap_rounds": 1,
        "outcome": 1,
        "failure_rate": 0.1
    },
    "circuit600.qasm": {
        "outcome_sum": 2,
        "n_failed_trap_rounds": 0,
        "outcome": 0,
        "failure_rate": 0.0
    },
    "circuit374.qasm": {
        "outcome_sum": 4,
        "n_failed_trap_rounds": 0,
        "outcome": 0,
        "failure_rate": 0.0
    },
    "circuit603.qasm": {
        "outcome_sum": 0,
        "n_failed_trap_rounds": 1,
        "outcome": 0,
        "failure_rate": 0.1
    },
    "circuit602.qasm": {
        "outcome_sum": 10,
        "n_failed_trap_rounds": 0,
        "outcome": 1,
        "failure_rate": 0.0
    },
    "circuit053.qasm": {
        "outcome_sum": 3,
        "n_failed_trap_rounds": 0,
        "outcome": 0,
        "failure_rate": 0.0
    },
    "circuit511.qasm": {
        "outcome_sum": 4,
        "n_failed_trap_rounds": 1,
        "outcome": 0,
        "failure_rate": 0.1
    },
    "circuit450.qasm": {
        "outcome_sum": 4,
        "n_failed_trap_rounds": 1,
        "outcome": 0,
        "failure_rate": 0.1
    },
    "circuit884.qasm": {
        "outcome_sum": 5,
        "n_failed_trap_rounds": 3,
        "outcome": "Ambig.",
        "failure_rate": 0.3
    },
    "circuit524.qasm": {
        "outcome_sum": 2,
        "n_failed_trap_rounds": 0,
        "outcome": 0,
        "failure_rate": 0.0
    },
    "circuit406.qasm": {
        "outcome_sum": 6,
        "n_failed_trap_rounds": 1,
        "outcome": 1,
        "failure_rate": 0.1
    }
}